MANIFEST.in
README.txt
setup.py
auslfe/__init__.py
auslfe.formonline.tokenaccess.egg-info/PKG-INFO
auslfe.formonline.tokenaccess.egg-info/SOURCES.txt
auslfe.formonline.tokenaccess.egg-info/dependency_links.txt
auslfe.formonline.tokenaccess.egg-info/entry_points.txt
auslfe.formonline.tokenaccess.egg-info/namespace_packages.txt
auslfe.formonline.tokenaccess.egg-info/not-zip-safe
auslfe.formonline.tokenaccess.egg-info/requires.txt
auslfe.formonline.tokenaccess.egg-info/top_level.txt
auslfe/formonline/__init__.py
auslfe/formonline/tokenaccess/__init__.py
auslfe/formonline/tokenaccess/configure.zcml
auslfe/formonline/tokenaccess/sharing_provider.py
auslfe/formonline/tokenaccess/browser/__init__.py
auslfe/formonline/tokenaccess/browser/approve.pt
auslfe/formonline/tokenaccess/browser/approve.py
auslfe/formonline/tokenaccess/browser/change_state_commands.pt
auslfe/formonline/tokenaccess/browser/configure.zcml
auslfe/formonline/tokenaccess/browser/tinyview.pt
auslfe/formonline/tokenaccess/browser/view.py
auslfe/formonline/tokenaccess/browser/viewlet.py
auslfe/formonline/tokenaccess/locales/auslfe.formonline.tokenaccess.pot
auslfe/formonline/tokenaccess/locales/i18n.sh
auslfe/formonline/tokenaccess/locales/it/LC_MESSAGES/auslfe.formonline.tokenaccess.mo
auslfe/formonline/tokenaccess/locales/it/LC_MESSAGES/auslfe.formonline.tokenaccess.po
docs/HISTORY.txt
docs/INSTALL.txt
docs/LICENSE.GPL
docs/LICENSE.txt