Metadata-Version: 1.0
Name: auslfe.formonline.tokenaccess
Version: 0.3.0
Summary: Plone add-on that enable anonymous use (with secret token) of auslfe.formonline features
Home-page: http://plone.org/products/auslfe.formonline.pfgadapter
Author: RedTurtle Technology
Author-email: sviluppoplone@redturtle.it
License: GPL
Keywords: plonegov form plone token
Platform: UNKNOWN
Classifier: Framework :: Plone
Classifier: Framework :: Plone :: 3.3
Classifier: Programming Language :: Python
Classifier: Development Status :: 4 - Beta
